AbdomenAtlas/__init__.py
AbdomenAtlas/assemble.py
AbdomenAtlas/create_attention.py
AbdomenAtlas/create_dataset.py
AbdomenAtlas/generate_datalist.py
AbdomenAtlas/test.py
AbdomenAtlas/train.py
AbdomenAtlas/dataset/__init__.py
AbdomenAtlas/dataset/dataloader.py
AbdomenAtlas/dataset/dataloader_test.py
AbdomenAtlas/dataset/dataloader_tumor.py
AbdomenAtlas/dataset/dataloader_validation.py
AbdomenAtlas/dataset/utils.py
AbdomenAtlas/document/__init__.py
AbdomenAtlas/model/DiNTS.py
AbdomenAtlas/model/SwinUNETR.py
AbdomenAtlas/model/SwinUNETR_partial.py
AbdomenAtlas/model/Unet.py
AbdomenAtlas/model/Universal_model.py
AbdomenAtlas/model/__init__.py
AbdomenAtlas/optimizers/__init__.py
AbdomenAtlas/optimizers/lr_scheduler.py
AbdomenAtlas/result/__init__.py
AbdomenAtlas/utils/__init__.py
AbdomenAtlas/utils/assemble.py
AbdomenAtlas/utils/cal_volume.py
AbdomenAtlas/utils/calculate_attention.py
AbdomenAtlas/utils/check_completeness.py
AbdomenAtlas/utils/combine_gif.py
AbdomenAtlas/utils/compute_dice.py
AbdomenAtlas/utils/dice_nsd.py
AbdomenAtlas/utils/label_transfer.py
AbdomenAtlas/utils/loss.py
AbdomenAtlas/utils/plot_video.py
AbdomenAtlas/utils/utils.py
AbdomenAtlas-0.1.1.dist-info/LICENSE
AbdomenAtlas-0.1.1.dist-info/METADATA
AbdomenAtlas-0.1.1.dist-info/WHEEL
AbdomenAtlas-0.1.1.dist-info/top_level.txt
AbdomenAtlas-0.1.1.dist-info/RECORD
