Metadata-Version: 2.1
Name: AbdomenAtlas
Version: 0.1.1
Summary: A package for 3D medical image segmentation using deep learning techniques.
Classifier: Programming Language :: Python :: 3
Classifier: License :: OSI Approved :: MIT License
Classifier: Operating System :: OS Independent
Requires-Python: >=3.6
License-File: LICENSE
Requires-Dist: connected-components-3d==3.18.0
Requires-Dist: fastremap==1.15.0
Requires-Dist: h5py==3.11.0
Requires-Dist: imageio==2.35.1
Requires-Dist: matplotlib==3.9.2
Requires-Dist: monai==1.2.0
Requires-Dist: nibabel==5.2.1
Requires-Dist: numpy==2.1.0
Requires-Dist: opencv-python==4.10.0.84
Requires-Dist: pandas==2.2.2
Requires-Dist: Pillow==10.4.0
Requires-Dist: scipy==1.14.1
Requires-Dist: tensorboardX==2.6.2.2
Requires-Dist: torch==2.4.0
Requires-Dist: tqdm==4.66.5
